launchable/__init__.py
launchable/__main__.py
launchable/app.py
launchable/testpath.py
launchable/version.py
launchable/commands/__init__.py
launchable/commands/detect_flakes.py
launchable/commands/helper.py
launchable/commands/split_subset.py
launchable/commands/subset.py
launchable/commands/test_path_writer.py
launchable/commands/verify.py
launchable/commands/compare/__init__.py
launchable/commands/compare/subsets.py
launchable/commands/inspect/__init__.py
launchable/commands/inspect/model.py
launchable/commands/inspect/subset.py
launchable/commands/inspect/tests.py
launchable/commands/record/__init__.py
launchable/commands/record/attachment.py
launchable/commands/record/build.py
launchable/commands/record/case_event.py
launchable/commands/record/commit.py
launchable/commands/record/session.py
launchable/commands/record/tests.py
launchable/commands/stats/__init__.py
launchable/commands/stats/test_sessions.py
launchable/jar/exe_deploy.jar
launchable/plugins/__init__.py
launchable/test_runners/__init__.py
launchable/test_runners/adb.py
launchable/test_runners/ant.py
launchable/test_runners/bazel.py
launchable/test_runners/behave.py
launchable/test_runners/codeceptjs.py
launchable/test_runners/ctest.py
launchable/test_runners/cts.py
launchable/test_runners/cucumber.py
launchable/test_runners/cypress.py
launchable/test_runners/dotnet.py
launchable/test_runners/file.py
launchable/test_runners/flutter.py
launchable/test_runners/go_test.py
launchable/test_runners/googletest.py
launchable/test_runners/gradle.py
launchable/test_runners/jasmine.py
launchable/test_runners/jest.py
launchable/test_runners/karma.py
launchable/test_runners/launchable.py
launchable/test_runners/maven.py
launchable/test_runners/minitest.py
launchable/test_runners/nunit.py
launchable/test_runners/playwright.py
launchable/test_runners/prove.py
launchable/test_runners/pytest.py
launchable/test_runners/raw.py
launchable/test_runners/robot.py
launchable/test_runners/rspec.py
launchable-1.117.0.dist-info/licenses/LICENSE.txt
launchable-1.117.0.dist-info/METADATA
launchable-1.117.0.dist-info/WHEEL
launchable-1.117.0.dist-info/entry_points.txt
launchable-1.117.0.dist-info/top_level.txt
launchable-1.117.0.dist-info/RECORD
