Metadata-Version: 2.4
Name: launchable
Version: 1.117.0
Summary: Launchable CLI
Home-page: https://launchableinc.com/
Author: Launchable, Inc.
Author-email: info@launchableinc.com
License: Apache Software License v2
Classifier: Programming Language :: Python :: 3
Classifier: License :: OSI Approved :: Apache Software License
Classifier: Operating System :: OS Independent
Requires-Python: >=3.6
License-File: LICENSE.txt
Requires-Dist: click<8.1,>=8.0; python_version == "3.6"
Requires-Dist: click<8.2,>=8.1; python_version > "3.6"
Requires-Dist: dataclasses; python_version == "3.6"
Requires-Dist: requests>=2.25; python_version >= "3.6"
Requires-Dist: urllib3>=1.26
Requires-Dist: junitparser>=4.0.0
Requires-Dist: setuptools
Requires-Dist: more_itertools>=7.1.0; python_version >= "3.6"
Requires-Dist: python-dateutil
Requires-Dist: tabulate
Requires-Dist: importlib-metadata
Dynamic: license-file
